Metadata-Version: 2.1
Name: novaquery
Version: 1.4.0
Summary: A tool to query OpenStack nova for servers, using a json-friendly syntax
Home-page: https://github.com/dealfonso/novaquery
Author: Carlos A.
Author-email: caralla@upv.es
License: Apache 2.0
Keywords: openstack,virtual machine
Classifier: Development Status :: 4 - Beta
Classifier: Intended Audience :: System Administrators
Classifier: Topic :: Utilities
Classifier: License :: OSI Approved :: Apache Software License
Classifier: Programming Language :: Python :: 3
License-File: LICENSE
